fun.py
ajm_j-0.0.1.dist-info/LICENSE
ajm_j-0.0.1.dist-info/METADATA
ajm_j-0.0.1.dist-info/WHEEL
ajm_j-0.0.1.dist-info/top_level.txt
ajm_j-0.0.1.dist-info/RECORD
