Metadata-Version: 2.1
Name: ajm-j
Version: 0.0.1
Summary: Say hello!
Home-page: https://github.com/jayaunyauni/jaya.git
Author: Jaya Unyauni
Author-email: jayaunyauni9999@gmail.com
License: UNKNOWN
Platform: UNKNOWN
Classifier: Programming Language :: Python :: 3
Classifier: License :: OSI Approved :: MIT License
Classifier: Operating System :: OS Independent
License-File: LICENSE
